ag_grid/__init__.py
ag_grid/admin.py
ag_grid/api.py
ag_grid/consumers.py
ag_grid/grid.py
ag_grid/log.py
ag_grid/models.py
ag_grid/permissions.py
ag_grid/registry.py
ag_grid/resource.py
ag_grid/routing.py
ag_grid/serializers.py
ag_grid/urls.py
ag_grid/utils.py
ag_grid/contrib/notification/__init__.py
ag_grid/contrib/notification/admin.py
ag_grid/contrib/notification/api.py
ag_grid/contrib/notification/apps.py
ag_grid/contrib/notification/consumers.py
ag_grid/contrib/notification/models.py
ag_grid/contrib/notification/signals.py
ag_grid/contrib/notification/urls.py
ag_grid/contrib/notification/utils.py
ag_grid/contrib/notification/__pycache__/__init__.cpython-311.pyc
ag_grid/contrib/notification/__pycache__/__init__.cpython-312.pyc
ag_grid/contrib/notification/__pycache__/admin.cpython-311.pyc
ag_grid/contrib/notification/__pycache__/admin.cpython-312.pyc
ag_grid/contrib/notification/__pycache__/api.cpython-311.pyc
ag_grid/contrib/notification/__pycache__/api.cpython-312.pyc
ag_grid/contrib/notification/__pycache__/apps.cpython-311.pyc
ag_grid/contrib/notification/__pycache__/apps.cpython-312.pyc
ag_grid/contrib/notification/__pycache__/consumers.cpython-311.pyc
ag_grid/contrib/notification/__pycache__/consumers.cpython-312.pyc
ag_grid/contrib/notification/__pycache__/models.cpython-311.pyc
ag_grid/contrib/notification/__pycache__/models.cpython-312.pyc
ag_grid/contrib/notification/__pycache__/signals.cpython-311.pyc
ag_grid/contrib/notification/__pycache__/signals.cpython-312.pyc
ag_grid/contrib/notification/__pycache__/urls.cpython-311.pyc
ag_grid/contrib/notification/__pycache__/urls.cpython-312.pyc
ag_grid/contrib/notification/__pycache__/utils.cpython-311.pyc
ag_grid/contrib/notification/__pycache__/utils.cpython-312.pyc
ag_grid/contrib/notification/migrations/0001_initial.py
ag_grid/contrib/notification/migrations/__init__.py
ag_grid/contrib/notification/migrations/__pycache__/0001_initial.cpython-311.pyc
ag_grid_django-0.0.7.83.dist-info/METADATA
ag_grid_django-0.0.7.83.dist-info/WHEEL
ag_grid_django-0.0.7.83.dist-info/top_level.txt
ag_grid_django-0.0.7.83.dist-info/RECORD
